Metadata-Version: 1.0
Name: packagenamemarcoshr
Version: 0.1
Summary: prueba prueba
Home-page: UNKNOWN
Author: UNKNOWN
Author-email: UNKNOWN
License: UNKNOWN
Platform: UNKNOWN
